{"name":"build-javascript","namedChunkGroups":{"app":{"name":"app","assets":[{"name":"webpack-runtime-404aa92ac86e7630cbb9.js","size":4402},{"name":"styles.62c78344e2a06e353067.css","size":371888},{"name":"framework-e1920fffb1cf79c01553.js","size":140793},{"name":"app-d8e81781d6142f031879.js","size":65210}],"filteredAssets":0,"assetsSize":582293,"filteredAuxiliaryAssets":48,"auxiliaryAssetsSize":1478692},"component---src-pages-404-js":{"name":"component---src-pages-404-js","assets":[{"name":"styles.62c78344e2a06e353067.css","size":371888},{"name":"252f366e-1ad51c56575cff947032.js","size":1111},{"name":"1bfc9850-53fdc498008eb7dc15a9.js","size":4691},{"name":"commons-abfeb7c0406b7eb91e42.js","size":28397},{"name":"component---src-pages-404-js-fb4de754179901770e28.js","size":1041}],"filteredAssets":0,"assetsSize":407128,"filteredAuxiliaryAssets":49,"auxiliaryAssetsSize":4645495},"component---src-pages-about-js":{"name":"component---src-pages-about-js","assets":[{"name":"styles.62c78344e2a06e353067.css","size":371888},{"name":"252f366e-1ad51c56575cff947032.js","size":1111},{"name":"1bfc9850-53fdc498008eb7dc15a9.js","size":4691},{"name":"commons-abfeb7c0406b7eb91e42.js","size":28397},{"name":"component---src-pages-about-js-925c10738046acc36904.js","size":4440}],"filteredAssets":0,"assetsSize":410527,"filteredAuxiliaryAssets":49,"auxiliaryAssetsSize":4649695},"component---src-pages-index-js":{"name":"component---src-pages-index-js","assets":[{"name":"styles.62c78344e2a06e353067.css","size":371888},{"name":"252f366e-1ad51c56575cff947032.js","size":1111},{"name":"1bfc9850-53fdc498008eb7dc15a9.js","size":4691},{"name":"commons-abfeb7c0406b7eb91e42.js","size":28397},{"name":"component---src-pages-index-js-ad824c74b275bfd3feae.js","size":2421}],"filteredAssets":0,"assetsSize":408508,"filteredAuxiliaryAssets":49,"auxiliaryAssetsSize":4649988},"component---src-pages-learning-js":{"name":"component---src-pages-learning-js","assets":[{"name":"styles.62c78344e2a06e353067.css","size":371888},{"name":"252f366e-1ad51c56575cff947032.js","size":1111},{"name":"1bfc9850-53fdc498008eb7dc15a9.js","size":4691},{"name":"commons-abfeb7c0406b7eb91e42.js","size":28397},{"name":"3e8e37fe8474b1216eb0da02864d9fec066bee6b-637cc991f41c4771057b.js","size":10631},{"name":"component---src-pages-learning-js-4a510ac258d96ea7bd12.js","size":3219}],"filteredAssets":0,"assetsSize":419937,"filteredAuxiliaryAssets":50,"auxiliaryAssetsSize":4720994},"component---src-pages-search-results-js":{"name":"component---src-pages-search-results-js","assets":[{"name":"styles.62c78344e2a06e353067.css","size":371888},{"name":"252f366e-1ad51c56575cff947032.js","size":1111},{"name":"1bfc9850-53fdc498008eb7dc15a9.js","size":4691},{"name":"commons-abfeb7c0406b7eb91e42.js","size":28397},{"name":"component---src-pages-search-results-js-1cd4c0dea8bdddfe485d.js","size":9382}],"filteredAssets":0,"assetsSize":415469,"filteredAuxiliaryAssets":49,"auxiliaryAssetsSize":4678075},"component---src-templates-blog-list-js":{"name":"component---src-templates-blog-list-js","assets":[{"name":"styles.62c78344e2a06e353067.css","size":371888},{"name":"252f366e-1ad51c56575cff947032.js","size":1111},{"name":"1bfc9850-53fdc498008eb7dc15a9.js","size":4691},{"name":"commons-abfeb7c0406b7eb91e42.js","size":28397},{"name":"component---src-templates-blog-list-js-9191662a8edae02e87fa.js","size":2593}],"filteredAssets":0,"assetsSize":408680,"filteredAuxiliaryAssets":49,"auxiliaryAssetsSize":4651346},"component---src-templates-post-js":{"name":"component---src-templates-post-js","assets":[{"name":"styles.62c78344e2a06e353067.css","size":371888},{"name":"252f366e-1ad51c56575cff947032.js","size":1111},{"name":"1bfc9850-53fdc498008eb7dc15a9.js","size":4691},{"name":"commons-abfeb7c0406b7eb91e42.js","size":28397},{"name":"3e8e37fe8474b1216eb0da02864d9fec066bee6b-637cc991f41c4771057b.js","size":10631},{"name":"component---src-templates-post-js-7ee750dc74533c7c73ec.js","size":2233}],"filteredAssets":0,"assetsSize":418951,"filteredAuxiliaryAssets":50,"auxiliaryAssetsSize":4719764}},"assetsByChunkName":{"app":["webpack-runtime-404aa92ac86e7630cbb9.js","styles.62c78344e2a06e353067.css","framework-e1920fffb1cf79c01553.js","app-d8e81781d6142f031879.js"],"component---src-pages-404-js":["styles.62c78344e2a06e353067.css","252f366e-1ad51c56575cff947032.js","1bfc9850-53fdc498008eb7dc15a9.js","commons-abfeb7c0406b7eb91e42.js","component---src-pages-404-js-fb4de754179901770e28.js"],"component---src-pages-about-js":["styles.62c78344e2a06e353067.css","252f366e-1ad51c56575cff947032.js","1bfc9850-53fdc498008eb7dc15a9.js","commons-abfeb7c0406b7eb91e42.js","component---src-pages-about-js-925c10738046acc36904.js"],"component---src-pages-index-js":["styles.62c78344e2a06e353067.css","252f366e-1ad51c56575cff947032.js","1bfc9850-53fdc498008eb7dc15a9.js","commons-abfeb7c0406b7eb91e42.js","component---src-pages-index-js-ad824c74b275bfd3feae.js"],"component---src-pages-learning-js":["styles.62c78344e2a06e353067.css","252f366e-1ad51c56575cff947032.js","1bfc9850-53fdc498008eb7dc15a9.js","commons-abfeb7c0406b7eb91e42.js","3e8e37fe8474b1216eb0da02864d9fec066bee6b-637cc991f41c4771057b.js","component---src-pages-learning-js-4a510ac258d96ea7bd12.js"],"component---src-pages-search-results-js":["styles.62c78344e2a06e353067.css","252f366e-1ad51c56575cff947032.js","1bfc9850-53fdc498008eb7dc15a9.js","commons-abfeb7c0406b7eb91e42.js","component---src-pages-search-results-js-1cd4c0dea8bdddfe485d.js"],"component---src-templates-blog-list-js":["styles.62c78344e2a06e353067.css","252f366e-1ad51c56575cff947032.js","1bfc9850-53fdc498008eb7dc15a9.js","commons-abfeb7c0406b7eb91e42.js","component---src-templates-blog-list-js-9191662a8edae02e87fa.js"],"component---src-templates-post-js":["styles.62c78344e2a06e353067.css","252f366e-1ad51c56575cff947032.js","1bfc9850-53fdc498008eb7dc15a9.js","commons-abfeb7c0406b7eb91e42.js","3e8e37fe8474b1216eb0da02864d9fec066bee6b-637cc991f41c4771057b.js","component---src-templates-post-js-7ee750dc74533c7c73ec.js"]},"childAssetsByChunkName":{}}